pybeyopticaltracker/__init__.py
pybeyopticaltracker-0.0.1.dist-info/LICENSE.txt
pybeyopticaltracker-0.0.1.dist-info/METADATA
pybeyopticaltracker-0.0.1.dist-info/WHEEL
pybeyopticaltracker-0.0.1.dist-info/top_level.txt
pybeyopticaltracker-0.0.1.dist-info/RECORD
